setuptools_pyproject_migration/__init__.py
setuptools_pyproject_migration/_long_description.py
setuptools_pyproject_migration/_types.py
setuptools_pyproject_migration/cli.py
setuptools_pyproject_migration-0.3.1.post0.dist-info/LICENSE
setuptools_pyproject_migration-0.3.1.post0.dist-info/METADATA
setuptools_pyproject_migration-0.3.1.post0.dist-info/WHEEL
setuptools_pyproject_migration-0.3.1.post0.dist-info/entry_points.txt
setuptools_pyproject_migration-0.3.1.post0.dist-info/top_level.txt
setuptools_pyproject_migration-0.3.1.post0.dist-info/RECORD
