Metadata-Version: 2.1
Name: setuptools-pyproject-migration
Version: 0.3.1.post0
Summary: Create a pyproject.toml file from setuptools configuration
Home-page: https://github.com/diazona/setuptools-pyproject-migration
Author: David Zaslavsky, Stuart Longland
Author-email: diazona@ellipsix.net, me@vk4msl.com
Project-URL: Documentation, https://setuptools-pyproject-migration.readthedocs.io/
Project-URL: Source, https://github.com/diazona/setuptools-pyproject-migration
Project-URL: Issues, https://github.com/diazona/setuptools-pyproject-migration/issues
Classifier: Development Status :: 3 - Alpha
Classifier: Environment :: Plugins
Classifier: Framework :: Setuptools Plugin
Classifier: Intended Audience :: Developers
Classifier: License :: OSI Approved :: MIT License
Classifier: Programming Language :: Python :: 3
Classifier: Programming Language :: Python :: 3 :: Only
Classifier: Topic :: Software Development
Classifier: Topic :: System :: Archiving :: Packaging
Requires-Python: >=3.6
License-File: LICENSE
Requires-Dist: packaging
Requires-Dist: pep508-parser
Requires-Dist: tomlkit
Requires-Dist: typing-extensions <5,>=4
Requires-Dist: setuptools ; python_version < "3.12"
Requires-Dist: dataclasses ; python_version < "3.7"
Requires-Dist: setuptools >=66.1 ; python_version >= "3.12"
Provides-Extra: docs
Requires-Dist: sphinx >=3.5 ; extra == 'docs'
Requires-Dist: jaraco.packaging >=9.3 ; extra == 'docs'
Requires-Dist: rst.linker >=1.9 ; extra == 'docs'
Requires-Dist: furo ; extra == 'docs'
Requires-Dist: sphinx-lint ; extra == 'docs'
Requires-Dist: sphinx-copybutton ; extra == 'docs'
Provides-Extra: testing
Requires-Dist: pytest >=7 ; extra == 'testing'
Requires-Dist: pytest-console-scripts >=1.2 ; extra == 'testing'
Requires-Dist: pytest-cov ; extra == 'testing'
Requires-Dist: requests ; extra == 'testing'
Requires-Dist: types-setuptools ; extra == 'testing'
Requires-Dist: backports.cached-property ; (python_version < "3.8") and extra == 'testing'
Requires-Dist: importlib-metadata ; (python_version < "3.8") and extra == 'testing'
Requires-Dist: pyproject-metadata ; (python_version >= "3.7") and extra == 'testing'
Requires-Dist: pytest-enabler >=2.2 ; (python_version >= "3.8") and extra == 'testing'
